README.md
setup.cfg
setup.py
waste_not_the_water/__init__.py
waste_not_the_water/app_datavis.py
waste_not_the_water/app_mlmodel.py
waste_not_the_water/app_ui.py
waste_not_the_water/basemap.py
waste_not_the_water/datacleaning.py
waste_not_the_water/due.py
waste_not_the_water/linear_regression.py
waste_not_the_water/nearest_n.py
waste_not_the_water/temperature.py
waste_not_the_water/version.py
waste_not_the_water.egg-info/PKG-INFO
waste_not_the_water.egg-info/SOURCES.txt
waste_not_the_water.egg-info/dependency_links.txt
waste_not_the_water.egg-info/requires.txt
waste_not_the_water.egg-info/top_level.txt
waste_not_the_water/data/T_UWWTPS.csv
waste_not_the_water/data/__init__.py
waste_not_the_water/data/clean.csv
waste_not_the_water/tests/__init__.py
waste_not_the_water/tests/test_basemap.py
waste_not_the_water/tests/test_linear_regression.py
waste_not_the_water/tests/test_nearest_n.py