Metadata-Version: 1.1
Name: waste-not-the-water
Version: 1.1
Summary: waste_not_the_water: a data science tool for wastewater treatment
Home-page: https://github.com/parkec3/waste_not_the_water
Author: Caitlin Parke
Author-email: parkec3@uw.edu
License: MIT
Download-URL: https://github.com/parkec3/waste_not_the_water/tags
Platform: OS Independent
Classifier: Development Status :: 2 - Pre-Alpha
Classifier: Environment :: Console
Classifier: Intended Audience :: Science/Research
Classifier: License :: OSI Approved :: MIT License
Classifier: Natural Language :: English
Classifier: Operating System :: OS Independent
Classifier: Programming Language :: Python
Classifier: Topic :: Scientific/Engineering
Requires: numpy
